searxng_wrapper/__init__.py
searxng_wrapper/client.py
searxng_wrapper/core/__init__.py
searxng_wrapper/core/logger.py
searxng_wrapper/types/__init__.py
searxng_wrapper/types/search.py
searxng_wrapper-0.1.1.dist-info/LICENSE
searxng_wrapper-0.1.1.dist-info/METADATA
searxng_wrapper-0.1.1.dist-info/WHEEL
searxng_wrapper-0.1.1.dist-info/RECORD
