Metadata-Version: 2.3
Name: searxng-wrapper
Version: 0.1.1
Summary: searxng-wrapper is a simple Python wrapper for interacting with SearXNG , a privacy-focused meta search engine. This library allows you to perform searches and retrieve structured results easily, without manually handling HTTP requests.
License: MIT
Author: arosyihuddin
Author-email: arosyihuddin6@gmail.com
Requires-Python: >=3.12
Classifier: License :: OSI Approved :: MIT License
Classifier: Programming Language :: Python :: 3
Classifier: Programming Language :: Python :: 3.12
Classifier: Programming Language :: Python :: 3.13
Requires-Dist: aiohttp (>=3.11.18,<4.0.0)
Requires-Dist: colorama (>=0.4.6,<0.5.0)
Requires-Dist: pydantic (>=2.11.4,<3.0.0)
Requires-Dist: requests (>=2.32.3,<3.0.0)
